{
  "pages": [
    {
      "path": "pages/index",
      "type": "home",
      "style": {
        "navigationBarTitleText": "我的课程"
      }
    },
    {
      "path": "pages/all-courses/index",
      "type": "page",
      "style": {
        "navigationStyle": "custom",
        "navigationBarTitleText": "其他课程"
      }
    },
    {
      "path": "pages/course-detail/index",
      "type": "page",
      "style": {
        "navigationBarTitleText": "课程详情",
        "navigationStyle": "custom"
      }
    },
    {
      "path": "pages/create-checkin/index",
      "type": "page",
      "style": {
        "navigationBarTitleText": "创建签到",
        "navigationStyle": "custom"
      }
    },
    {
      "path": "pages/create-course/index",
      "type": "page",
      "style": {
        "navigationBarTitleText": "创建课程",
        "navigationStyle": "custom"
      }
    },
    {
      "path": "pages/join-course/index",
      "type": "page",
      "style": {
        "navigationStyle": "custom",
        "navigationBarTitleText": "加入课程"
      }
    },
    {
      "path": "pages/login/index",
      "type": "page"
    },
    {
      "path": "pages/my/index",
      "type": "page",
      "layout": "tabbar",
      "name": "my",
      "style": {
        "navigationBarTitleText": "个人中心"
      }
    },
    {
      "path": "pages/register/index",
      "type": "page"
    },
    {
      "path": "pages/scanner/index",
      "type": "page",
      "style": {
        "navigationStyle": "custom",
        "navigationBarTitleText": "扫码签到"
      }
    }
  ],
  "globalStyle": {
    "navigationBarTitleText": "Wot-Demo",
    "navigationBarTextStyle": "white",
    "navigationStyle": "custom"
  },
  "tabBar": {
    "custom": true,
    "height": "0",
    "color": "#bfbfbf",
    "selectedColor": "#0165FF",
    "list": [
      {
        "pagePath": "pages/index"
      },
      {
        "pagePath": "pages/my/index"
      }
    ]
  },
  "subPackages": []
}
